TechFinder/__init__.py
TechFinder/detector.py
techfinder-0.3.2.dist-info/LICENSE
techfinder-0.3.2.dist-info/METADATA
techfinder-0.3.2.dist-info/WHEEL
techfinder-0.3.2.dist-info/top_level.txt
techfinder-0.3.2.dist-info/RECORD
