Metadata-Version: 2.2
Name: techfinder
Version: 0.3.2
Summary: A Python library to detect technologies used by websites
Home-page: https://github.com/Prathameshsci369/Detector
Author: Prathamesh B Anand
Author-email: prathameshsci963@gmai.com
Classifier: Programming Language :: Python :: 3
Classifier: Programming Language :: Python :: 3.12
Classifier: License :: OSI Approved :: MIT License
Classifier: Operating System :: OS Independent
Requires-Python: >=3.6
License-File: LICENSE
Requires-Dist: requests==2.28.2
Requires-Dist: beautifulsoup4==4.12.2
Dynamic: author
Dynamic: author-email
Dynamic: classifier
Dynamic: description
Dynamic: description-content-type
Dynamic: home-page
Dynamic: requires-dist
Dynamic: requires-python
Dynamic: summary
